django_path2css-0.2.3.dist-info/DESCRIPTION.rst
django_path2css-0.2.3.dist-info/LICENSE.txt
django_path2css-0.2.3.dist-info/METADATA
django_path2css-0.2.3.dist-info/RECORD
django_path2css-0.2.3.dist-info/WHEEL
django_path2css-0.2.3.dist-info/metadata.json
django_path2css-0.2.3.dist-info/top_level.txt
path2css/__init__.py
path2css/templatetags/__init__.py
path2css/templatetags/path2css.py
path2css/tests/__init__.py
path2css/tests/test_context_processor.py
path2css/tests/test_deprecations.py
path2css/tests/test_templatetag_css4path.py
path2css/tests/test_templatetag_path2css.py
