Metadata-Version: 2.0
Name: django-path2css
Version: 0.2.3
Summary: Convert a request.path ('/a/b/c/d/') into CSS class names
Home-page: https://github.com/kezabelle/django-path2css
Author: Keryn Knight
Author-email: django-path2css@kerynknight.com
License: BSD License
Keywords: django path2css
Platform: UNKNOWN
Classifier: Development Status :: 3 - Alpha
Classifier: Intended Audience :: Developers
Classifier: License :: OSI Approved :: BSD License
Classifier: Natural Language :: English
Classifier: Programming Language :: Python :: 2
Classifier: Programming Language :: Python :: 2.7
Classifier: Programming Language :: Python :: 3
Classifier: Programming Language :: Python :: 3.3
Classifier: Programming Language :: Python :: 3.4
Classifier: Programming Language :: Python :: 3.5
Classifier: Framework :: Django
Classifier: Framework :: Django :: 1.10
Classifier: Framework :: Django :: 1.8
Classifier: Framework :: Django :: 1.9
Requires-Dist: Django (>=1.8)
